scalarmodels/__init__.py
scalarmodels/ann.py
scalarmodels/chi.py
scalarmodels/cnn.py
scalarmodels/comparison.py
scalarmodels/gru.py
scalarmodels/lstm.py
scalarmodels/paralle.py
scalarmodels/resnet.py
scalarmodel-0.1.1.dist-info/METADATA
scalarmodel-0.1.1.dist-info/WHEEL
scalarmodel-0.1.1.dist-info/top_level.txt
scalarmodel-0.1.1.dist-info/RECORD
