Metadata-Version: 2.4
Name: scalarmodel
Version: 0.1.1
Summary: My ML functions for California Housing and Fashion MNIST
Home-page: 
Author: sch
Requires-Dist: numpy
Requires-Dist: pandas
Requires-Dist: matplotlib
Requires-Dist: scikit-learn
Requires-Dist: tensorflow
Requires-Dist: seaborn
Dynamic: author
Dynamic: requires-dist
Dynamic: summary
